sort_reference/SortReference.py
sort_reference/__init__.py
sort_reference/__main__.py
sort_reference-0.1.2.dist-info/LICENSE
sort_reference-0.1.2.dist-info/METADATA
sort_reference-0.1.2.dist-info/WHEEL
sort_reference-0.1.2.dist-info/top_level.txt
sort_reference-0.1.2.dist-info/RECORD
