Metadata-Version: 2.1
Name: sort-reference
Version: 0.1.2
Summary: Sort reference by cited order in docx file
Home-page: https://github.com/Casxt/SortReference
Author: casxt
Author-email: maple@forer.cn
License: UNKNOWN
Platform: UNKNOWN
Classifier: Development Status :: 3 - Alpha
Classifier: Intended Audience :: Developers
Classifier: Programming Language :: Python :: 3
Classifier: License :: OSI Approved :: Apache Software License
Classifier: Operating System :: OS Independent
Requires-Python: >=3.6
Requires-Dist: lxml (>=4.8.0)
